doughnut/__init__.py
doughnut/hello.py
doughnut-0.0.1.dist-info/METADATA
doughnut-0.0.1.dist-info/WHEEL
doughnut-0.0.1.dist-info/top_level.txt
doughnut-0.0.1.dist-info/RECORD
