Metadata-Version: 2.1
Name: doughnut
Version: 0.0.1
Summary: Library for NLP data
Home-page: UNKNOWN
Author: Abdulsalam Bande
Author-email: <abdulsalambande@gmail.com>
License: UNKNOWN
Keywords: python,numpy,nlp,machine learning
Platform: UNKNOWN
Classifier: Development Status :: 1 - Planning
Classifier: Intended Audience :: Developers
Classifier: Programming Language :: Python :: 3
Classifier: Operating System :: Unix
Classifier: Operating System :: MacOS :: MacOS X
Classifier: Operating System :: Microsoft :: Windows
